pyatf/__init__.py
pyatf/range.py
pyatf/result_check.py
pyatf/search_space.py
pyatf/tp.py
pyatf/tuner.py
pyatf/tuning_data.py
pyatf/abort_conditions/__init__.py
pyatf/abort_conditions/abort_condition.py
pyatf/abort_conditions/cost.py
pyatf/abort_conditions/duration.py
pyatf/abort_conditions/evaluations.py
pyatf/abort_conditions/fraction.py
pyatf/abort_conditions/speedup.py
pyatf/cost_functions/__init__.py
pyatf/cost_functions/cuda.py
pyatf/cost_functions/generic.py
pyatf/cost_functions/opencl.py
pyatf/cost_functions/python.py
pyatf/search_techniques/__init__.py
pyatf/search_techniques/auc_bandit.py
pyatf/search_techniques/differential_evolution.py
pyatf/search_techniques/exhaustive.py
pyatf/search_techniques/opentuner.py
pyatf/search_techniques/pattern_search.py
pyatf/search_techniques/random.py
pyatf/search_techniques/round_robin.py
pyatf/search_techniques/search_technique.py
pyatf/search_techniques/search_technique_1d.py
pyatf/search_techniques/simulated_annealing.py
pyatf/search_techniques/torczon.py
pyatf-0.0.11.dist-info/METADATA
pyatf-0.0.11.dist-info/WHEEL
pyatf-0.0.11.dist-info/licenses/LICENSE
pyatf-0.0.11.dist-info/RECORD
