Metadata-Version: 2.4
Name: pyatf
Version: 0.0.11
Summary: Auto-Tuning Framework (ATF) is a generic, general-purpose auto-tuning approach for programs whose tuning parameters may be constrained
Project-URL: Homepage, https://atf-project.org/
Project-URL: Issues, https://github.com/atf-tuner/pyATF/issues
Author-email: Richard Schulze <r.schulze@uni-muenster.de>, Ari Rasch <a.rasch@uni-muenster.de>
License-File: LICENSE
Keywords: auto-tuning,constraints,optimization,performance,tuning
Classifier: License :: OSI Approved :: MIT License
Classifier: Operating System :: OS Independent
Classifier: Programming Language :: Python :: 3
Requires-Python: >=3.9
